yta_image_advanced_filters/__init__.py
yta_image_advanced_filters/gameboy.py
yta_image_advanced_filters/motion_blur.py
yta_image_advanced_filters/pixelate.py
yta_image_advanced_filters/sketch/__init__.py
yta_image_advanced_filters/sketch/workers/__init__.py
yta_image_advanced_filters/sketch/workers/filters.py
yta_image_advanced_filters/sketch/workers/linedraw.py
yta_image_advanced_filters/sketch/workers/perlin.py
yta_image_advanced_filters/sketch/workers/strokesort.py
yta_image_advanced_filters/sketch/workers/util.py
yta_image_advanced_filters/sticker.py
yta_image_advanced_filters-0.0.5.dist-info/LICENSE
yta_image_advanced_filters-0.0.5.dist-info/METADATA
yta_image_advanced_filters-0.0.5.dist-info/WHEEL
yta_image_advanced_filters-0.0.5.dist-info/RECORD
